setup.cfg
setup.py
pyworkingdays.egg-info/PKG-INFO
pyworkingdays.egg-info/SOURCES.txt
pyworkingdays.egg-info/dependency_links.txt
pyworkingdays.egg-info/requires.txt
pyworkingdays.egg-info/top_level.txt
workingdays/__init__.py
workingdays/l10n/__init__.py
workingdays/l10n/it.py