Metadata-Version: 1.1
Name: pyworkingdays
Version: 0.1
Summary: Utility functions to deal with working days in date operations. With builtin localization support.
Home-page: https://github.com/baxeico/pyworkingdays
Author: Augusto Destrero
Author-email: a.destrero@gmail.com
License: UNKNOWN
Download-URL: https://github.com/baxeico/pyworkingdays/archive/0.1.tar.gz
Keywords: date,business,working
Platform: UNKNOWN
